FITX/__init__.py
FITX/_version.py
FITX/fitting.py
FITX-1.0.1.dist-info/LICENSE
FITX-1.0.1.dist-info/METADATA
FITX-1.0.1.dist-info/WHEEL
FITX-1.0.1.dist-info/top_level.txt
FITX-1.0.1.dist-info/RECORD
