Metadata-Version: 2.1
Name: FITX
Version: 1.0.1
Summary: Fit my InsTability eXponential
Home-page: https://github.com/aoeftiger/FITX
Author: Adrian Oeftiger
Author-email: adrian@oeftiger.net
License: MIT
Platform: UNKNOWN
Classifier: Programming Language :: Python :: 2.6
Classifier: Programming Language :: Python :: 2.7
Classifier: Programming Language :: Python :: 3
Classifier: License :: OSI Approved :: MIT License
Classifier: Operating System :: OS Independent
Requires-Python: >=2.6
